{
  "title": "Uchi no otouto-domo ga sumimasen",
  "description": "Ito's mother remarried and begins her new life as an older sister of 4 siblings!\nThe start of a family-love-comedy with four step-brothers ♥",
  "artist": "OZAKI Akira ",
  "author": "OZAKI Akira ",
  "cover": "https://mangadex.org/covers/b9c16c69-df27-4c6e-9676-8a260403758f/695600ed-8cba-47b0-b807-b0f0dd024b2c.jpg",
  "chapters": {
    "01": {
      "title": "Capitolo 1",
      "volume": "1",
      "last_updated": "1656911661",
      "groups": {
        "": "/proxy/api/imgur/chapter/EXZyuZn"
      }
    },
    "02": {
      "title": "Capitolo 2",
      "volume": "1",
      "last_updated": "1656912140",
      "groups": {
        "": "/proxy/api/imgur/chapter/RePTRpY"
      }
    },
    "03": {
      "title": "Capitolo 3",
      "volume": "1",
      "last_updated": "1656914651",
      "groups": {
        "": "/proxy/api/imgur/chapter/C8TjNxu"
      }
    },
    "04": {
      "title": "Capitolo 4",
      "volume": "1",
      "last_updated": "1656914911",
      "groups": {
        "": "/proxy/api/imgur/chapter/lmWNjNc"
      }
    },
    "05": {
      "title": "Capitolo 5",
      "volume": "2",
      "last_updated": "1656916630",
      "groups": {
        "": "/proxy/api/imgur/chapter/iP8i6ru"
      }
    },
    "06": {
      "title": "Capitolo 6",
      "volume": "2",
      "last_updated": "1656917070",
      "groups": {
        "": "/proxy/api/imgur/chapter/VMR9EH9"
      }
    },
    "07": {
      "title": "Capitolo 7",
      "volume": "2",
      "last_updated": "1656917369",
      "groups": {
        "": "/proxy/api/imgur/chapter/Ak3i6SB"
      }
    },
    "08": {
      "title": "Capitolo 8",
      "volume": "2",
      "last_updated": "1656917618",
      "groups": {
        "": "/proxy/api/imgur/chapter/JBlfliD"
      }
    }
  }
}